{
	"metadata": {
		"name": "Sunan Ibn Majah",
		"section": {
			"37": "Zuhd"
		}
	},
	"hadiths": [
		{
			"hadithnumber": 4100,
			"arabicnumber": 4100,
			"text": "১/৪১০০। আবূ যারা আল-গিফারী (রাঃ) থেকে বর্ণিত। তিনি বলেন, রাসূলুল্লাহ সাল্লাল্লাহু আলাইহি ওয়াসাল্লাম বলেছেনঃ হালাল বস্ত্তুকে হারাম করে নেয়া এবং ধনসম্পদ ধ্বংস করা দুনিয়ার প্রতি অনাসক্তি (যুহ্দ) নয়, বরং দুনিয়ার প্রতি অনাসক্তি হলোঃ আল্লাহর নিকট যা আছে তার চেয়ে তোমার নিকট যা আছে তার উপর অধিক নির্ভরশীল না হওয়া এবং তুমি কোন বিপদে পতিত হলে তার বিনিময়ে সওয়াবের আশার তুলনায় বিপদে পতিত না হওয়াটা তোমার নিকট অধিকতর কাঙ্ক্ষিত না হওয়া। হিশাম (রাঃ) বলেন, আবূ ইদরীস আল-খাওলানী (রাঃ) বলেছেন, হাদীস ভান্ডারে এ হাদীসটি যেন স্বর্ণ খনির খাঁটি সোনা।",
			"grades": [
				{
					"name": "Al-Albani",
					"grade": "Very Daif"
				},
				{
					"name": "Muhammad Fouad Abd al-Baqi",
					"grade": "Very Daif"
				},
				{
					"name": "Shuaib Al Arnaut",
					"grade": "Very Daif"
				},
				{
					"name": "Zubair Ali Zai",
					"grade": "Daif"
				}
			],
			"reference": {
				"book": 37,
				"hadith": 1
			}
		}
	]
}