{
	"metadata": {
		"name": "Sahih al Bukhari",
		"section": {
			"46": "Oppressions"
		}
	},
	"hadiths": [
		{
			"hadithnumber": 2463,
			"arabicnumber": 2463,
			"text": "Ebu Hureyre r.a.'den rivayet edilmiştir: Allah Resulü Sallallahu Aleyhi ve Sellem \"Komşu, komşusunun duvarına bir tahta koymasına engel olmasın\" buyurmuştur. Sonra Ebu Hureyre şöyle demiştir: \"Niye sizin bundan yüz çevirdiğinizi görüyorum. Allah'a yemin ederim ki ben bu tahtayı sizin omuzlarınız arasına koyacağım\" demiştir. Tekrar: 5627, 5628 Diğer tahric: Tirmizi Ahkan; İbn Mâce, Ahkâm",
			"grades": [],
			"reference": {
				"book": 46,
				"hadith": 24
			}
		}
	]
}