{
	"metadata": {
		"name": "Sahih al Bukhari",
		"section": {
			"64": "Military Expeditions led by the Prophet (pbuh) (Al-Maghaazi)"
		}
	},
	"hadiths": [
		{
			"hadithnumber": 4445,
			"arabicnumber": 4445,
			"text": "ez-Zuhrî, yine geçen senedle şöyle demiştir: Bana Ubeydullah haber verdi ki, Âişe (r.anha) şöyle demiştir: Yemîn olsun ben \"Ebû Bekr insanlara imâm olup namaz kıldırsın\" emri hususunda Rasûlüllah'a çok müracaat ettim. Beni Rasûlüllah'a çok müracaat etmeye sevkeden düşünce şu idi: Rasûlüllah'ın makaamına geçecek kimseyi insanların devamlı sevebileceğini gönlüm bir türlü almıyordu. Ve öyle sanıyordum ki, Rasûlüllah'ın yerine geçecek kimseyi insanlar muhakkak uğursuz sayacaklardır. İşte bunun için ben Rasûlüllah'ın, Ebû Bekr'in imamlık yapmasına dâir emrini ta'dîl etmesini ısrarla istemiştim. Ebû Bekr'in insanlara namaz kıldırması emri hadîsini İbnu Omer, Ebû Mûsâ, İbn Abbâs -Allah onlardan razı olsun- Peygamber'den rivayet etmişlerdir",
			"grades": [],
			"reference": {
				"book": 64,
				"hadith": 465
			}
		}
	]
}