{"metadata":{"name":"Sunan Abu Dawud","section":{"40":"Prescribed Punishments (Kitab Al-Hudud)"}},"hadiths":[{"hadithnumber":4387,"arabicnumber":4387,"text":"عبداللہ بن عباس رضی اللہ عنہما کہتے ہیں کہ رسول اللہ صلی اللہ علیہ وسلم نے ایک شخص کا ہاتھ ایک ڈھال کے ( چرانے پر ) کاٹا جس کی قیمت ایک دینار یا دس درہم تھی۔","grades":[{"name":"Al-Albani","grade":"Daif"},{"name":"Muhammad Muhyi Al-Din Abdul Hamid","grade":"Shadh"},{"name":"Shuaib Al Arnaut","grade":"Daif"},{"name":"Zubair Ali Zai","grade":"Daif"}],"reference":{"book":40,"hadith":37}}]}