{
	"metadata": {
		"name": "Jami At Tirmidhi",
		"section": {
			"14": "The Book on Business"
		}
	},
	"hadiths": [
		{
			"hadithnumber": 1220,
			"arabicnumber": 1220,
			"text": "حدثنا هناد، حدثنا ابن المبارك، أخبرنا سليمان التيمي، عن أبي عثمان، عن ابن مسعود، عن النبي صلى الله عليه وسلم أنه نهى عن تلقي البيوع ‏.‏ قال وفي الباب عن علي وابن عباس وأبي هريرة وأبي سعيد وابن عمر ورجل من أصحاب النبي صلى الله عليه وسلم ‏.‏",
			"grades": [
				{
					"name": "Ahmad Muhammad Shakir",
					"grade": "Sahih"
				},
				{
					"name": "Al-Albani",
					"grade": "Sahih"
				},
				{
					"name": "Zubair Ali Zai",
					"grade": "Sahih"
				}
			],
			"reference": {
				"book": 14,
				"hadith": 19
			}
		}
	]
}