{
	"metadata": {
		"name": "Jami At Tirmidhi",
		"section": {
			"7": "The Book on Zakat"
		}
	},
	"hadiths": [
		{
			"hadithnumber": 662,
			"arabicnumber": 662,
			"text": "حدثنا أبو كريب، محمد بن العلاء حدثنا وكيع، حدثنا عباد بن منصور، حدثنا القاسم بن محمد، قال سمعت أبا هريرة، يقول قال رسول الله صلى الله عليه وسلم ‏\"‏ إن الله يقبل الصدقة ويأخذها بيمينه فيربيها لأحدكم كما يربي أحدكم مهره حتى إن اللقمة لتصير مثل أحد ‏\"‏ ‏.‏ وتصديق ذلك في كتاب الله عز وجل ‏(‏وهو الذي يقبل التوبة عن عباده ‏)‏ ويأخذ الصدقات‏‏ ‏(يمحق الله الربا ويربي الصدقات‏)‏‏.‏ قال أبو عيسى: هذا حديث حسن صحيح. وقد روي عن عائشة عن النبي صلى الله عليه وسلم نحو هذا. وقد قال غير واحد من أهل العلم في هذا الحديث وما يشبه هذا من الروايات من الصفات ونزول الرب تبارك وتعالى كل ليلة إلى السماء الدنيا قالوا قد تثبت الروايات في هذا ويؤمن بها ولا يتوهم ولا يقال كيف هكذا روي عن مالك وسفيان بن عيينة وعبد الله بن المبارك أنهم قالوا في هذه الأحاديث أمروها بلا كيف. وهكذا قول أهل العلم من أهل السنة والجماعة. وأما الجهمية فأنكرت هذه الروايات وقالوا هذا تشبيه. وقد ذكر الله عز وجل في غير موضع من كتابه اليد والسمع والبصر فتأولت الجهمية هذه الآيات ففسروها على غير ما فسر أهل العلم وقالوا إن الله لم يخلق آدم بيده. وقالوا إن معنى اليد هاهنا القوة. وقال إسحاق بن إبراهيم إنما يكون التشبيه إذا قال يد كيد أو مثل يد أو سمع كسمع أو مثل سمع. فإذا قال سمع كسمع أو مثل سمع فهذا التشبيه وأما إذا قال كما قال الله تعالى يد وسمع وبصر ولا يقول كيف ولا يقول مثل سمع ولا كسمع فهذا لا يكون تشبيها وهو كما قال الله تعالى في كتابه: {ليس كمثله شيء وهو السميع البصير}",
			"grades": [
				{
					"name": "Ahmad Muhammad Shakir",
					"grade": "Munqar"
				},
				{
					"name": "Al-Albani",
					"grade": "Munqar"
				},
				{
					"name": "Zubair Ali Zai",
					"grade": "Daif"
				}
			],
			"reference": {
				"book": 7,
				"hadith": 46
			}
		}
	]
}