{"metadata":{"name":"Sunan Abu Dawud","section":{"34":"Clothing (Kitab Al-Libas)"}},"hadiths":[{"hadithnumber":4050,"arabicnumber":4050,"text":"حَدَّثَنَا يَحْيَى بْنُ حَبِيبٍ، حَدَّثَنَا رَوْحٌ، حَدَّثَنَا هِشَامٌ، عَنْ مُحَمَّدٍ، عَنْ عُبَيْدَةَ، عَنْ عَلِيٍّ، - رضى الله عنه - أَنَّهُ قَالَ نَهَى عَنْ مَيَاثِرِ الأُرْجُوَانِ ‏.‏","grades":[{"name":"Al-Albani","grade":"Sahih"},{"name":"Muhammad Muhyi Al-Din Abdul Hamid","grade":"Sahih"},{"name":"Shuaib Al Arnaut","grade":"Sahih"},{"name":"Zubair Ali Zai","grade":"Sahih"}],"reference":{"book":34,"hadith":31}}]}