{
	"metadata": {
		"name": "Sunan Abu Dawud",
		"section": {
			"35": "Combing the Hair (Kitab Al-Tarajjul)"
		}
	},
	"hadiths": [
		{
			"hadithnumber": 4194,
			"arabicnumber": 4194,
			"text": "حَدَّثَنَا مُوسَى بْنُ إِسْمَاعِيلَ، حَدَّثَنَا حَمَّادٌ، حَدَّثَنَا أَيُّوبُ، عَنْ نَافِعٍ، عَنِ ابْنِ عُمَرَ، أَنَّ النَّبِيَّ صلى الله عليه وسلم نَهَى عَنِ الْقَزَعِ وَهُوَ أَنْ يُحْلَقَ رَأْسُ الصَّبِيِّ فَتُتْرَكَ لَهُ ذُؤَابَةٌ ‏.‏",
			"grades": [
				{
					"name": "Al-Albani",
					"grade": "Sahih"
				},
				{
					"name": "Muhammad Muhyi Al-Din Abdul Hamid",
					"grade": "Sahih"
				},
				{
					"name": "Zubair Ali Zai",
					"grade": "Isnaad Sahih"
				}
			],
			"reference": {
				"book": 35,
				"hadith": 36
			}
		}
	]
}