{
	"metadata": {
		"name": "Muwatta Malik",
		"section": {
			"10": "The Two 'Ids"
		}
	},
	"hadiths": [
		{
			"hadithnumber": 432,
			"arabicnumber": 432,
			"text": "وحدثني عن مالك، عن ابن شهاب، عن أبي عبيد، مولى ابن أزهر قال شهدت العيد مع عمر بن الخطاب فصلى ثم انصرف فخطب الناس فقال إن هذين يومان نهى رسول الله صلى الله عليه وسلم عن صيامهما يوم فطركم من صيامكم والآخر يوم تأكلون فيه من نسككم ‏.‏ قال أبو عبيد ثم شهدت العيد مع عثمان بن عفان فجاء فصلى ثم انصرف فخطب وقال إنه قد اجتمع لكم في يومكم هذا عيدان فمن أحب من أهل العالية أن ينتظر الجمعة فلينتظرها ومن أحب أن يرجع فقد أذنت له ‏.‏ قال أبو عبيد ثم شهدت العيد مع علي بن أبي طالب - وعثمان محصور - فجاء فصلى ثم انصرف فخطب ‏.‏",
			"grades": [
				{
					"name": "Salim al-Hilali",
					"grade": "Mauquf Sahih"
				}
			],
			"reference": {
				"book": 10,
				"hadith": 432
			}
		}
	]
}