{
	"metadata": {
		"name": "Sunan Abu Dawud",
		"section": {
			"3": "The Book Of The Prayer For Rain (Kitab al-Istisqa')"
		}
	},
	"hadiths": [
		{
			"hadithnumber": 1169,
			"arabicnumber": 1169,
			"text": "Telah menceritakan kepada kami [Ibnu Abu Khalaf] telah menceritakan kepada kami [Muhammad bin 'Ubaid] telah menceritakan kepada kami [Mis'ar] dari [Yazid Al Faqir] dari [Jabir bin Abdillah] dia berkata; \"Beberapa wanita mendatangi Rasulullah shallallahu 'alaihi wasallam sambil menangis (karena kekeringan), kemudian beliau berdo'a: \"Allahummasqina ghaitsan mughitsan mari'an nafi'an ghair dharrin 'ajilan ghaira ajilin\" (ya Allah, turunkanlah kepada kami hujan yang dapat menolong kami, yang menyenangkan kami, menyuburkan lagi bermanfaat dan tidak membahayakan, segera jangan ditunda-tunda).\" Seketika itu juga, langit menurunkan hujannya atas mereka",
			"grades": [
				{
					"name": "Al-Albani",
					"grade": "Sahih"
				},
				{
					"name": "Muhammad Muhyi Al-Din Abdul Hamid",
					"grade": "Sahih"
				},
				{
					"name": "Shuaib Al Arnaut",
					"grade": "Hasan"
				},
				{
					"name": "Zubair Ali Zai",
					"grade": "Isnaad Hasan"
				}
			],
			"reference": {
				"book": 3,
				"hadith": 9
			}
		}
	]
}