{
	"metadata": {
		"name": "Sunan Abu Dawud",
		"section": {
			"14": "Fasting (Kitab Al-Siyam)"
		}
	},
	"hadiths": [
		{
			"hadithnumber": 2473,
			"arabicnumber": 2473,
			"text": "Telah menceritakan kepada kami [Wahb bin Baqiyyah], telah mengabarkan kepada kami [Khalid], dari [Abdurrahman bin Ishaq] dari [Az Zuhri], dari ['Urwah] dari [Aisyah] bahwa ia berkata; yang disunahkan atas orang yang beri'tikaf adalah tidak menjenguk orang yang sedang sakit, serta tidak mengiringi jenazah serta tidak menyentuh wanita, tidak bercampur dengannya dan tidak keluar untuk suatu keperluan kecuali karena sesuatu yang harus ia lakukan. Dan tidak ada i'tikaf kecuali disertai puasa dan tidak ada i'tikaf kecuali di Masjid yang padanya dilakukan shalat Jum'at. Abu Daud berkata; selain Abdurrahman tidak mengatakan padanya; tidak Aisyah berkata; yang disunahkan. Abu Daud berkata; ia menjadikannya sebagai perkataan Aisyah",
			"grades": [
				{
					"name": "Al-Albani",
					"grade": "Hasan Sahih"
				},
				{
					"name": "Muhammad Muhyi Al-Din Abdul Hamid",
					"grade": "Hasan Sahih"
				},
				{
					"name": "Shuaib Al Arnaut",
					"grade": "Hasan"
				},
				{
					"name": "Zubair Ali Zai",
					"grade": "Daif"
				}
			],
			"reference": {
				"book": 14,
				"hadith": 161
			}
		}
	]
}