{
	"metadata": {
		"name": "Sahih Muslim",
		"section": {
			"15": "The Book of Pilgrimage"
		}
	},
	"hadiths": [
		{
			"hadithnumber": 2900,
			"arabicnumber": "1206.10",
			"text": "حدثنا هارون بن عبد الله، حدثنا الأسود بن عامر، عن زهير، عن أبي الزبير، قال سمعت سعيد بن جبير، يقول قال ابن عباس - رضى الله عنهما - وقصت رجلا راحلته وهو مع رسول الله صلى الله عليه وسلم فأمرهم رسول الله صلى الله عليه وسلم أن يغسلوه بماء وسدر وأن يكشفوا وجهه - حسبته قال - ورأسه فإنه يبعث يوم القيامة وهو يهل ‏.‏",
			"grades": [],
			"reference": {
				"book": 15,
				"hadith": 109
			}
		}
	]
}