{
	"metadata": {
		"name": "Muwatta Malik",
		"section": {
			"20": "Hajj"
		}
	},
	"hadiths": [
		{
			"hadithnumber": 769,
			"arabicnumber": 769,
			"text": "وَحَدَّثَنِي عَنْ مَالِكٍ، عَنْ نَافِعٍ، عَنْ عَبْدِ اللَّهِ بْنِ عُمَرَ، أَنَّ عُمَرَ بْنَ الْخَطَّابِ، قَالَ افْصِلُوا بَيْنَ حَجِّكُمْ وَعُمْرَتِكُمْ فَإِنَّ ذَلِكَ أَتَمُّ لِحَجِّ أَحَدِكُمْ وَأَتَمُّ لِعُمْرَتِهِ أَنْ يَعْتَمِرَ فِي غَيْرِ أَشْهُرِ الْحَجِّ ‏.‏",
			"grades": [
				{
					"name": "Salim al-Hilali",
					"grade": "Mauquf Sahih"
				}
			],
			"reference": {
				"book": 20,
				"hadith": 769
			}
		}
	]
}