{"metadata":{"name":"Jami At Tirmidhi","section":{"15":"The Chapters On Judgements From The Messenger of Allah"}},"hadiths":[{"hadithnumber":1373,"arabicnumber":1373,"text":"Zaid bin Khalid Al-Juhni narrated that the Messenger of Allah (ﷺ) was asked about the lost item. He said:\"Make a public announcement about it for one year, if it is claimed then give it to him. Otherwise remember its sack, string, and its count. Then use it, and if its owner comes, give it to him","grades":[{"name":"Ahmad Muhammad Shakir","grade":"Sahih"},{"name":"Al-Albani","grade":"Sahih"},{"name":"Bashar Awad Maarouf","grade":"Hasan Sahih"},{"name":"Zubair Ali Zai","grade":"Sahih"}],"reference":{"book":15,"hadith":54}}]}