{
	"metadata": {
		"name": "Sunan Ibn Majah",
		"section": {
			"6": "Chapters Regarding Funerals"
		}
	},
	"hadiths": [
		{
			"hadithnumber": 1506,
			"arabicnumber": 1506,
			"text": "عمرو بن عوف مزنی رضی اللہ عنہ کہتے ہیں کہ رسول اللہ صلی اللہ علیہ وسلم نے پانچ تکبیرات کہیں۔",
			"grades": [
				{
					"name": "Al-Albani",
					"grade": "Sahih"
				},
				{
					"name": "Muhammad Fouad Abd al-Baqi",
					"grade": "Sahih Lighairihi"
				},
				{
					"name": "Zubair Ali Zai",
					"grade": "Hasan Or Sahih"
				}
			],
			"reference": {
				"book": 6,
				"hadith": 74
			}
		}
	]
}