{"metadata":{"name":"Sunan Ibn Majah","section":{"32":"Chapters on Dress"}},"hadiths":[{"hadithnumber":3635,"arabicnumber":3635,"text":"ام المؤمنین عائشہ رضی اللہ عنہا کہتی ہیں کہ رسول اللہ صلی اللہ علیہ وسلم کے بال مونڈھوں سے اوپر اور کانوں سے نیچے ہوتے تھے۔","grades":[{"name":"Al-Albani","grade":"Hasan"},{"name":"Muhammad Fouad Abd al-Baqi","grade":"Hasan"},{"name":"Shuaib Al Arnaut","grade":"Hasan Sahih"},{"name":"Zubair Ali Zai","grade":"Hasan Or Sahih"}],"reference":{"book":32,"hadith":86}}]}