{
	"metadata": {
		"name": "Sunan an Nasai",
		"section": {
			"5": "The Book of Salah"
		}
	},
	"hadiths": [
		{
			"hadithnumber": 454,
			"arabicnumber": 454,
			"text": "Abu 'Amr - meaning, Al-Awza'i - said that he asked Az-Zuhri about the prayer of the Messenger of Allah (ﷺ) in Makkah before the Hijrah to Al-Madinah. He said:\"Urwah told me that 'Aishah said: 'Allah enjoined the salah upon the Messenger of Allah (ﷺ), and the first thing that He enjoined was two Rak'ahs at a time, then it was made complete four Rak'ahs while in the state of residence but the prayer when traveling remained two Rak'ahs, as it was first enjoined",
			"grades": [
				{
					"name": "Abu Ghuddah",
					"grade": "Sahih"
				},
				{
					"name": "Al-Albani",
					"grade": "Sahih"
				},
				{
					"name": "Zubair Ali Zai",
					"grade": "Hasan Or Sahih"
				}
			],
			"reference": {
				"book": 5,
				"hadith": 7
			}
		}
	]
}