{"metadata":{"name":"Sunan an Nasai","section":{"45":"The Book of Oaths (qasamah), Retaliation and Blood Money"}},"hadiths":[{"hadithnumber":4837,"arabicnumber":4837,"text":"It was narrated from Al-Ash'ath bin sulaim, from his father that a man from among Banu Tha'labah bin Yarbu' said:\"I came to the Prophet when he was speaking, and a man said: 'O Messenger of Allah, these are Banu Tha'labah bin Yarbu' who killed so and so.' The Messenger of Allah said: 'No,' meaning no soul is affected by the sin of another","grades":[{"name":"Abu Ghuddah","grade":"Sahih"},{"name":"Al-Albani","grade":"Sahih"},{"name":"Zubair Ali Zai","grade":"Hasan Or Sahih"}],"reference":{"book":45,"hadith":132}}]}