{
	"metadata": {
		"name": "Sunan Abu Dawud",
		"section": {
			"11": "The Rites of Hajj (Kitab Al-Manasik Wa'l-Hajj)"
		}
	},
	"hadiths": [
		{
			"hadithnumber": 1879,
			"arabicnumber": 1879,
			"text": "Ebu't-Tufeyl'den; demiştir ki: Nebi (S.A.V.)'i hayvanı üzerinde (Hacer-i Esved'in bulunduğu) rüknü selamlayarak Beyt'i tavaf ederken gördüm. (Bu hadisi Ebû Davud'a rivayet eden diğer râvi) Muhammed b. Râfi de (bu rivayete şunu) ekledi: Sonra Safâ'ya ve Merve'ye çıktı, yedi defa (Safa ile Merve arasını) hayvanı üzerinde tavaf et­ti. Şunlarda rivayet etti: İbn Mâce, menâsik, Müslim, hac",
			"grades": [
				{
					"name": "Al-Albani",
					"grade": "Sahih"
				},
				{
					"name": "Muhammad Muhyi Al-Din Abdul Hamid",
					"grade": "Sahih"
				},
				{
					"name": "Zubair Ali Zai",
					"grade": "Sahih Muslim"
				}
			],
			"reference": {
				"book": 11,
				"hadith": 159
			}
		}
	]
}