{"metadata":{"name":"Sahih Muslim","section":{"6":"The Book of Prayer - Travellers"}},"hadiths":[{"hadithnumber":1591,"arabicnumber":"694.02","text":"{….} Bize bu hadîsi Züheyr b. Harb da rivayet etti. (Dediki): Bize Velîd b. Müslim, Evzâîden rivayet etti. H. Bize bu hadîsi İshâk ile Ahd b. Humeyd de rivayet ettiler. Dediler ki: Bize Abdürrezzâk haber verdi. (Dediki): Bize Ma'mer haber verdi. Bunlar hep birden Zührî'den bu isnâdla rivayet etmişlerdir. Zührî: «Mina'da» demiş: «başka yerlerde» dememiştir","grades":[],"reference":{"book":6,"hadith":22}}]}