{
	"metadata": {
		"name": "Sahih Muslim",
		"section": {
			"22": "The Book of Musaqah"
		}
	},
	"hadiths": [
		{
			"hadithnumber": 3964,
			"arabicnumber": "1551.03",
			"text": "(Bize İbn Nümeyr rivâyet etti. ki): Bize babam rivâyet etti. ki): Bize Ubeydullah rivâyet etti. ki): Bana Nâfi', Abdullah b. Ömer'den naklen rivâyet etti ki, Resûlüllah (sallallahü aleyhi ve sellem) Hayber halkına oradan çıkan ekin veya meyvenin yarısı mukabilinde muamele yapmış. hadîsi Alî b. Müshir rivâyeti gibi nakletmiş; yalnız: «Âişe ile Hafsa, arazî ve suyu ihtiyar edenlerdendi.» cümlesini zikretmemiş: «Peygamber (sallallahü aleyhi ve sellem)’in zevcelerini, kendilerine yer bölmek şartiyle muhayyer bıraktı.» demiş; suyu da zikretmemiştir",
			"grades": [],
			"reference": {
				"book": 22,
				"hadith": 3
			}
		}
	]
}