{
	"metadata": {
		"name": "Sahih Muslim",
		"section": {
			"29": "The Book of Legal Punishments"
		}
	},
	"hadiths": [
		{
			"hadithnumber": 4431,
			"arabicnumber": "1695.01",
			"text": "Bize Muhammed b. El-AIâ' El-Hemdânî rivayet etti. (Dediki): Bize Yahya b. Ya'lâ —kî İbni'l-Hâris El-Muhâribî'dir— Gaylân'dan (bu zât Câmiu'l-Muhâribî'nin oğludur.), o da Alkame b. Mersed'den, o da Süleyman b. Büreyde'den, o da babasından naklen rivayet etti. Babası şöyle demiş: Mâiz b. Mâlik Nebi (Sallallahu Aleyhi ve Sellem)'e gelerek: — Yâ Resûlâllah! Beni temizle! dedi. Bunun üzerine: «Vah sana! Dön de Allah'tan mağfiret dîlel Ona tevbe et!» buyurdu. (Mâiz) uzağa gitmemek üzere geri döndü. Sonra gelerek: — Yâ Resûlâllah! Beni temizle! dedi. Resulullah (Sallallahu Aleyhi ve Sellem) tekrar: «Vah sana! Dön de Allah'tan mağfiret dile! Ona tevbe et!» buyurdu. Mâiz yine uzağa gitmemek üzere geri döndü. Sonra gelerek: — Yâ Resûlâllah! Beni temizle! dedi. Nebi (Sallallahu Aleyhi ve Sellem) ona : «Seni ne hususta temizliyeyim?» diye sordu. Mâiz: — Zina'dan! dedi. Bunu müteâkib Resulullah (Sallallahu Aleyhi ve Sellem): «Bunda delilik var mı?» diye sordu. Kendilerine onun deli olmadığı haber verildi. «Şarab içmiş mi?» diye sordu. Hemen bir zât kalkarak onun ağzını kokladı; fakat şarap kokusu bulamadı. Resulullah (Sallallahu Aleyhi ve Sellem) tekrar: «Sen zina mı ettin?» diye sordu. Mâiz: — Evet! cevâbını verdi. Artık emir buyurdular ve Mâiz recmedildi. Onun hakkında cemaat iki fırka olmuştu. Kimisi: Helak oldu! Onu günahı kuşattı!., diyor; bazısı da: Mâiz'in tevbesinden efdal tevbe olmaz.!.. Zira o Nebi (Sallallahu Aleyhi ve Sellem)'e gelerek elini onun eline koydu. Sonra: Benî taşlarla öldür! dedi... diyordu. Bu minval üzere iki veya üç gün durdular. Bilâhare onlar otururken Resûlullah (Sallallahu Aleyhi ve Sellem) gelerek selâm verdi ve oturdu. Arkacığından: «Mâiz b. Mâlik için istiğfar edin!» buyurdular. Ashâb: — Allah Mâiz b. Mâlik'e mağfiret eylesin! dediler. Resûlullah (Sallallahu Aleyhi ve Sellem) de : «Gerçekten öyle bir tevbe etti ki, bu tevbe bir ümmet arasında taksim edilse onlara yeterdi.» buyurdu. Sonra Ezd kabilesinin Gâmid kolundan bir kadın geldi; ve : — Ya Resûlâllah! Beni temizle! dedi. «Vah sana!.. Dön de Allah'tan mağfiret dile! Ona tevbe et!» buyurdular,. Kadın: Görüyorum beni, Mâiz'i çevirdiğin gibi geri çevirmek istiyorsun, dedi. «Ne oldu sana?» diye sordu. Kadın kendisinin zinadan gebe olduğunu söyledi. Bunun üzerine: «Sen mi?» buyurdu. Kadın : — Evet! cevâbını verdi. Ona: «Karnındakini doğuruncaya kadar...» buyurdular. Derken kadın doğuruncaya kadar geçimini Ensârdan bir zât üzerine aldı. Bilâhare Peygamber (Sallallahu Aleyhi ve Sellem)'e gelerek: — Gâmid'li kadın doğurdu; dedi. Efendimiz : «O halde onu recmedip de çocuğunu küçük olduğu halde emzirecek kimsesiz bırakamayız!» buyurdu. Bunun üzerine Ensâr'dan bir zât ayağa kalkarak: — Çocuğun bakımı bana âid olsun ya Nebiyyaîlah! dedi. O da kadını recmetti(rdi)",
			"grades": [],
			"reference": {
				"book": 29,
				"hadith": 34
			}
		}
	]
}