{
	"metadata": {
		"name": "Sahih al Bukhari",
		"section": {
			"77": "Dress"
		}
	},
	"hadiths": [
		{
			"hadithnumber": 5880,
			"arabicnumber": 5880,
			"text": "Narrated Ibn `Abbas:I offered the `Id prayer with the Prophet (ﷺ) and he offered prayer before the Khutba (sermon). ibn `Abbas added: After the prayer the Prophet (ﷺ) came towards (the rows of) the women and ordered them to give alms, and the women started putting their big and small rings in the garment of Bilal",
			"grades": [],
			"reference": {
				"book": 77,
				"hadith": 97
			}
		}
	]
}