{
	"metadata": {
		"name": "Sahih al Bukhari",
		"section": {
			"3": "Knowledge"
		}
	},
	"hadiths": [
		{
			"hadithnumber": 99,
			"arabicnumber": 99,
			"text": "Narrated Abu Huraira:I said: \"O Allah's Messenger (ﷺ)! Who will be the luckiest person, who will gain your intercession on the Day of Resurrection?\" Allah's Messenger (ﷺ) said: O Abu Huraira! \"I have thought that none will ask me about it before you as I know your longing for the (learning of) Hadiths. The luckiest person who will have my intercession on the Day of Resurrection will be the one who said sincerely from the bottom of his heart \"None has the right to be worshipped but Allah",
			"grades": [],
			"reference": {
				"book": 3,
				"hadith": 41
			}
		}
	]
}