{"metadata":{"name":"Sahih al Bukhari","section":{"6":"Menstrual Periods"}},"hadiths":[{"hadithnumber":332,"arabicnumber":332,"text":"Telah menceritakan kepada kami [Ahmad bin Abu Suraij] berkata, telah mengabarkan kepada kami [Syababah] berkata, telah mengabarkan kepada kami [Syu'bah] dari [Husain Al Mu'alim] dari ['Abdullah bin Buraidah] dari [Samrah bin Jundub], bahwa ada seorang wanita yang meninggal dunia karena hamil. Maka Nabi shallallahu 'alaihi wasallam menshalatinya dan beliau berdiri di bagian tengah (jenazah) nya","grades":[],"reference":{"book":6,"hadith":36}}]}