{"metadata":{"name":"Sunan Ibn Majah","section":{"24":"The Chapters on Jihad"}},"hadiths":[{"hadithnumber":2849,"arabicnumber":2849,"text":"حدثنا هشام بن عمار، حدثنا سفيان بن عيينة، عن عمرو بن دينار، عن سالم بن أبي الجعد، عن عبد الله بن عمرو، قال كان على ثقل النبي صلى الله عليه وسلم رجل يقال له كركرة ‏.‏ فمات فقال النبي صلى الله عليه وسلم ‏ \"‏ هو في النار ‏\"‏ ‏.‏ فذهبوا ينظرون فوجدوا عليه كساء أو عباءة قد غلها ‏.‏","grades":[{"name":"Al-Albani","grade":"Sahih"},{"name":"Muhammad Fouad Abd al-Baqi","grade":"Sahih"},{"name":"Shuaib Al Arnaut","grade":"Sahih"},{"name":"Zubair Ali Zai","grade":"Hasan Or Sahih"}],"reference":{"book":24,"hadith":97}}]}