{
	"metadata": {
		"name": "Sunan an Nasai",
		"section": {
			"5": "The Book of Salah"
		}
	},
	"hadiths": [
		{
			"hadithnumber": 480,
			"arabicnumber": 480,
			"text": "أَخْبَرَنَا عُبَيْدُ اللَّهِ بْنُ سَعْدِ بْنِ إِبْرَاهِيمَ بْنِ سَعْدٍ، قَالَ حَدَّثَنِي عَمِّي، قَالَ حَدَّثَنَا أَبِي، عَنْ مُحَمَّدِ بْنِ إِسْحَاقَ، قَالَ حَدَّثَنِي يَزِيدُ بْنُ أَبِي حَبِيبٍ، عَنْ عِرَاكِ بْنِ مَالِكٍ، قَالَ سَمِعْتُ نَوْفَلَ بْنَ مُعَاوِيَةَ، يَقُولُ صَلاَةٌ مَنْ فَاتَتْهُ فَكَأَنَّمَا وُتِرَ أَهْلَهُ وَمَالَهُ ‏.‏ قَالَ ابْنُ عُمَرَ قَالَ رَسُولُ اللَّهِ صلى الله عليه وسلم ‏ \"‏ هِيَ صَلاَةُ الْعَصْرِ ‏\"‏ ‏.‏",
			"grades": [
				{
					"name": "Abu Ghuddah",
					"grade": "Sahih"
				},
				{
					"name": "Al-Albani",
					"grade": "Sahih"
				},
				{
					"name": "Zubair Ali Zai",
					"grade": "Hasan Or Sahih"
				}
			],
			"reference": {
				"book": 5,
				"hadith": 33
			}
		}
	]
}