{"metadata":{"name":"Sahih Muslim","section":{"37":"The Book of Clothes and Adornment"}},"hadiths":[{"hadithnumber":5435,"arabicnumber":"2077.02","text":"وَحَدَّثَنَا زُهَيْرُ بْنُ حَرْبٍ، حَدَّثَنَا يَزِيدُ بْنُ هَارُونَ، أَخْبَرَنَا هِشَامٌ، ح وَحَدَّثَنَا أَبُو بَكْرِ بْنُ أَبِي شَيْبَةَ حَدَّثَنَا وَكِيعٌ، عَنْ عَلِيِّ بْنِ الْمُبَارَكِ، كِلاَهُمَا عَنْ يَحْيَى بْنِ أَبِي كَثِيرٍ، بِهَذَا الإِسْنَادِ وَقَالاَ عَنْ خَالِدِ بْنِ مَعْدَانَ، ‏.‏","grades":[],"reference":{"book":37,"hadith":50}}]}