{
	"metadata": {
		"name": "Sahih al Bukhari",
		"section": {
			"6": "Menstrual Periods"
		}
	},
	"hadiths": [
		{
			"hadithnumber": 305,
			"arabicnumber": 305,
			"text": "حَدَّثَنَا أَبُو نُعَيْمٍ، قَالَ حَدَّثَنَا عَبْدُ الْعَزِيزِ بْنُ أَبِي سَلَمَةَ، عَنْ عَبْدِ الرَّحْمَنِ بْنِ الْقَاسِمِ، عَنِ الْقَاسِمِ بْنِ مُحَمَّدٍ، عَنْ عَائِشَةَ، قَالَتْ خَرَجْنَا مَعَ النَّبِيِّ صلى الله عليه وسلم لاَ نَذْكُرُ إِلاَّ الْحَجَّ، فَلَمَّا جِئْنَا سَرِفَ طَمِثْتُ، فَدَخَلَ عَلَىَّ النَّبِيُّ صلى الله عليه وسلم وَأَنَا أَبْكِي فَقَالَ ‏{‏مَا يُبْكِيكِ‏}‏‏.‏ قُلْتُ لَوَدِدْتُ وَاللَّهِ أَنِّي لَمْ أَحُجَّ الْعَامَ‏.‏ قَالَ ‏{‏لَعَلَّكِ نُفِسْتِ‏}‏‏.‏ قُلْتُ نَعَمْ‏.‏ قَالَ ‏ \"‏ فَإِنَّ ذَلِكَ شَىْءٌ كَتَبَهُ اللَّهُ عَلَى بَنَاتِ آدَمَ، فَافْعَلِي مَا يَفْعَلُ الْحَاجُّ، غَيْرَ أَنْ لاَ تَطُوفِي بِالْبَيْتِ حَتَّى تَطْهُرِي ‏\"‏‏.‏",
			"grades": [],
			"reference": {
				"book": 6,
				"hadith": 10
			}
		}
	]
}