{
	"metadata": {
		"name": "Sahih al Bukhari",
		"section": {
			"64": "Military Expeditions led by the Prophet (pbuh) (Al-Maghaazi)"
		}
	},
	"hadiths": [
		{
			"hadithnumber": 4239,
			"arabicnumber": 4239,
			"text": "حَدَّثَنَا مُوسَى بْنُ إِسْمَاعِيلَ، حَدَّثَنَا عَمْرُو بْنُ يَحْيَى بْنِ سَعِيدٍ، قَالَ أَخْبَرَنِي جَدِّي، أَنَّ أَبَانَ بْنَ سَعِيدٍ، أَقْبَلَ إِلَى النَّبِيِّ صلى الله عليه وسلم فَسَلَّمَ عَلَيْهِ، فَقَالَ أَبُو هُرَيْرَةَ يَا رَسُولَ اللَّهِ هَذَا قَاتِلُ ابْنِ قَوْقَلٍ‏.‏ وَقَالَ أَبَانُ لأَبِي هُرَيْرَةَ وَاعَجَبًا لَكَ وَبْرٌ تَدَأْدَأَ مِنْ قَدُومِ ضَأْنٍ‏.‏ يَنْعَى عَلَىَّ امْرَأً أَكْرَمَهُ اللَّهُ بِيَدِي، وَمَنَعَهُ أَنْ يُهِينَنِي بِيَدِهِ‏.‏",
			"grades": [],
			"reference": {
				"book": 64,
				"hadith": 277
			}
		}
	]
}