{
	"metadata": {
		"name": "Sahih al Bukhari",
		"section": {
			"70": "Food, Meals"
		}
	},
	"hadiths": [
		{
			"hadithnumber": 5456,
			"arabicnumber": 5456,
			"text": "حَدَّثَنَا عَلِيُّ بْنُ عَبْدِ اللَّهِ، حَدَّثَنَا سُفْيَانُ، عَنْ عَمْرِو بْنِ دِينَارٍ، عَنْ عَطَاءٍ، عَنِ ابْنِ عَبَّاسٍ، أَنَّ النَّبِيَّ صلى الله عليه وسلم قَالَ ‏ \"‏ إِذَا أَكَلَ أَحَدُكُمْ فَلاَ يَمْسَحْ يَدَهُ حَتَّى يَلْعَقَهَا أَوْ يُلْعِقَهَا ‏\"‏‏.‏",
			"grades": [],
			"reference": {
				"book": 70,
				"hadith": 85
			}
		}
	]
}