{
	"metadata": {
		"name": "Sahih al Bukhari",
		"section": {
			"77": "Dress"
		}
	},
	"hadiths": [
		{
			"hadithnumber": 5804,
			"arabicnumber": 5804,
			"text": "حَدَّثَنَا أَبُو نُعَيْمٍ، حَدَّثَنَا سُفْيَانُ، عَنْ عَمْرٍو، عَنْ جَابِرِ بْنِ زَيْدٍ، عَنِ ابْنِ عَبَّاسٍ، عَنِ النَّبِيِّ صلى الله عليه وسلم قَالَ ‏ \"‏ مَنْ لَمْ يَجِدْ إِزَارًا فَلْيَلْبَسْ سَرَاوِيلَ، وَمَنْ لَمْ يَجِدْ نَعْلَيْنِ فَلْيَلْبَسْ خُفَّيْنِ ‏\"‏‏.‏",
			"grades": [],
			"reference": {
				"book": 77,
				"hadith": 22
			}
		}
	]
}