{"metadata":{"name":"Sunan Ibn Majah","section":{"3":"The Book of the Adhan and the Sunnah Regarding It"}},"hadiths":[{"hadithnumber":715,"arabicnumber":715,"text":"Telah menceritakan kepada kami [Abu Bakr bin Abu Syaibah] berkata, telah menceritakan kepada kami [Muhammad bin Abdullah bin Al Asad] dari [Abu Isra`il] dari [Al Hakam] dari [Abdurrahman bin Abu Laila] dari [Bilal] ia berkata; \"Rasulullah shallallahu 'alaihi wasallam memerintahkan kepadaku untuk mengucapkan tatswib dalam shalat subuh dan melarang untuk mengucapkannya dalam shalat isya","grades":[{"name":"Al-Albani","grade":"Daif"},{"name":"Muhammad Fouad Abd al-Baqi","grade":"Daif"},{"name":"Shuaib Al Arnaut","grade":"Daif"},{"name":"Zubair Ali Zai","grade":"Daif"}],"reference":{"book":3,"hadith":10}}]}