{"metadata":{"name":"Sahih Muslim","section":{"15":"The Book of Pilgrimage"}},"hadiths":[{"hadithnumber":2972,"arabicnumber":"1226.01","text":"ہمیں اسماعیل بن ابراہیم نے حدیث بیا ن کی ، ( کہا : ) ہمیں جریری نے حدیث سنائی ، انھوں نے ابو العلاء سے ، انھوں نے مطرف سے روایت کی ، ( مطرف نے ) کہا : عمران بن حصین نے مجھ سے کہا : میں تمھیں آج ایک ایسی حدیث بیان کرنے لگاہوں جس سے اللہ تعالیٰ آج کے بعد تمھیں نفع دے گا ۔ جان لو! اللہ کے رسول صلی اللہ علیہ وسلم نے اپنے گھر والوں میں سے کچھ کو ذوالحجہ میں عمرہ کروایا ، پھر نہ تو کوئی ایسی آیت نازل ہوئی جس نے اسے ( حج کے مہینوںمیں عمرے کو ) منسوخ قرار دیا ہو ، اور نہ آپ صلی اللہ علیہ وسلم نے اس سے روکا ، حتیٰ کہ آپ صلی اللہ علیہ وسلم اپنی منزل کی طرف تشریف لے گئے ۔ بعد میں ہر شخص نے جورائے قائم کرنا چاہی کرلی ۔","grades":[],"reference":{"book":15,"hadith":181}}]}