{
	"metadata": {
		"name": "Sahih Muslim",
		"section": {
			"23": "The Book of the Rules of Inheritance"
		}
	},
	"hadiths": [
		{
			"hadithnumber": 4150,
			"arabicnumber": "1617.01",
			"text": "ہشام نے ہمیں حدیث بیان کی : ہمیں قتادہ نے سالم بن ابی جعد سے حدیث بیان کی ، انہوں نے معدان بن ابی طلحہ سے روایت کی کہ حضرت عمر بن خطاب رضی اللہ عنہ نے جمعہ کے دن خطبہ دیا ، انہوں نے نبی صلی اللہ علیہ وسلم کا تذکرہ کیا اور حضرت ابوبکر رضی اللہ عنہ کا تذکرہ کیا ، پھر کہا : میں اپنے بعد کوئی ایسی چیز نہیں چھوڑ رہا جو میرے ہاں کلالہ سے زیادہ اہم ہو ، میں نے رسول اللہ صلی اللہ علیہ وسلم سے کسی چیز کے بارے میں اتنی مراجعت نہیں کی جتنی کلالہ کے بارے میں کی ، اور آپ نے بھی مجھ سے کسی چیز کے بارے میں اتنی شدت اختیار نہیں فرمائی جتنی کلالہ کے بارے میں فرمائی حتی کہ آپ نے اپنی انگلی میرے سینے میں چبھوئی اور فرمایا : \" اے عمر! تمہیں موسم گرما ( میں نازل ہونے ) والی آیت کافی نہیں جو سورہ نساء کے آخر میں ہے؟ ( جس سے مسئلہ واضح ہو گیا ہے ) \" اور میں ( عمر ) اگر زندہ رہا تو اس کے بارے میں ایسا واضح فیصلہ کروں گا جس ( کو دیکھتے ہوئے ) ایسا شخص ( بھی ) فیصلہ کر سکے گا جو قرآن پڑھتا ( اور سمجھتا ) ہے اور وہ بھی جو قرآن نہیں پڑھتا ۔",
			"grades": [],
			"reference": {
				"book": 23,
				"hadith": 11
			}
		}
	]
}