{"metadata":{"name":"Sahih Muslim","section":{"45":"The Book of Virtue, Enjoining Good Manners, and Joining of the Ties of Kinship"}},"hadiths":[{"hadithnumber":6578,"arabicnumber":"2580","text":"سالم نے اپنے والد سے روایت کی ، کہا : رسول اللہ صلی اللہ علیہ وسلم نے فرمایا : \" مسلمان دوسرے مسلمان کا بھائی ہے ، نہ اس پر ظلم کرتا ہے ، نہ اسے ( ظالموں کے ) سپرد کرتا ہے ۔ جو شخص اپنے بھائی کی حاجت پوری کرنے میں لگا ہوتا ہے ، اللہ تعالیٰ اس کی حاجت روائی فرماتا ہے ۔ جو کسی مسلمان سے اس کی ایک تکلیف دور کرتا ہے ، اللہ تعالیٰ اس سے قیامت کی تکلیفوں میں سے ایک تکلیف دور کرتا ہے ۔ جو شخص کسی مسلمان کی پردہ پوشی کرتا ہے ، اللہ تعالیٰ قیامت کے دن اس ( کے عیبوں ) کی پردہ پوشی فرمائے گا ۔","grades":[],"reference":{"book":45,"hadith":76}}]}