{"metadata":{"name":"Sahih Muslim","section":{"22":"The Book of Musaqah"}},"hadiths":[{"hadithnumber":4006,"arabicnumber":"1566.01","text":"Telah menceritakan kepada kami [Yahya bin Yahya] dia berkata; saya bacakan di hadapan [Malik]. (dalam jalur lain disebutkan) Telah menceritakan kepada kami [Qutaibah] telah menceritakan kepada kami [Laits] keduanya dari [Abu Zinad] dari [Al A'raj] dari [Abu Hurairah], bahwa Rasulullah shallallahu 'alaihi wasallam bersabada: \"Dilarang menahan kelebihan air untuk mencegah tumbuhnya al kala` (rumput)","grades":[],"reference":{"book":22,"hadith":45}}]}