{
	"metadata": {
		"name": "Sahih Muslim",
		"section": {
			"33": "The Book on Government"
		}
	},
	"hadiths": [
		{
			"hadithnumber": 4798,
			"arabicnumber": "1852.03",
			"text": "Dan telah menceritakan kepadaku [Utsman bin Abu Syaibah] telah menceritakan kepada kami [Yunus bin Abu Ya'fur] dari [ayahnya] dari ['Arfajah] dia berkata, \"Saya mendengar Rasulullah shallallahu 'alaihi wasallam bersabda: \"Bila datang kepadamu seseorang yang hendak mematahkan tongkatmu (memecah belah jama'ah) atau memecah belah persatuan kalian, maka bunuhlah dia",
			"grades": [],
			"reference": {
				"book": 33,
				"hadith": 95
			}
		}
	]
}