{"metadata":{"name":"Sahih Muslim","section":{"51":"Characteristics of The Hypocrites And Rulings Concerning Them"}},"hadiths":[{"hadithnumber":7044,"arabicnumber":"2784.02","text":"হাদিস একাডেমি নাম্বারঃ ৬৯৩৭, আন্তর্জাতিক নাম্বারঃ ২৭৮৪ ৬৯৩৭-(…/...) কুতাইবাহ ইবনু সাঈদ (রহঃ) ..... ইবনু উমার থেকে বর্ণিত। তিনি নবী সাল্লাল্লাহু আলাইহি ওয়াসাল্লাম হতে অবিকল হাদীস বর্ণনা করেছেন। কিন্তু এতে রয়েছে, একবার আসে এ পালে আবার যায় অন্য পালে। (ইসলামিক ফাউন্ডেশন ৬৭৮৭, ইসলামিক সেন্টার, নেই)","grades":[],"reference":{"book":51,"hadith":21}}]}