{
	"metadata": {
		"name": "Sunan an Nasai",
		"section": {
			"20": "The Book of Qiyam Al-Lail (The Night Prayer) and Voluntary Prayers During the Day"
		}
	},
	"hadiths": [
		{
			"hadithnumber": 1699,
			"arabicnumber": 1699,
			"text": "Telah mengabarkan kepada kami ['Ali bin Maimun] dia berkata; telah menceritakan kepada kami [Makhlad bin Yazid] dari [Sufyan] dari [Zubaid] dari [Sa'id bin 'Abdurrahman bin Abza] dari [Bapaknya] dari [Ubay bin Ka'ab] bahwa Rasulullah shallallahu 'alaihi wasallam pernah shalat witir tiga rakaat, pada rakaat pertama beliau membaca: \": Sabbihisma rabbikal a'laa (surah Al A'la).\" Pada rakaat kedua membaca: \"Qul ya ayyuhal kafirun (surah Al Kaafiruun), \" dan pada rakaat ketiga beliau membaca \"Qul huwallahu ahad (surah Al Ikhlas).\" Lalu beliau qunut sebelum ruku'. Setelah selesai beliau membaca \"Subbhanal Malikil Quddus\" tiga kali. Beliau memanjangkan pada yang terakhir kalinya",
			"grades": [
				{
					"name": "Abu Ghuddah",
					"grade": "Sahih"
				},
				{
					"name": "Al-Albani",
					"grade": "Sahih"
				},
				{
					"name": "Zubair Ali Zai",
					"grade": "Hasan Or Sahih"
				}
			],
			"reference": {
				"book": 20,
				"hadith": 102
			}
		}
	]
}