{"metadata":{"name":"Sahih al Bukhari","section":{"18":"Shortening the Prayers (At-Taqseer)"}},"hadiths":[{"hadithnumber":1119,"arabicnumber":1119,"text":"حدثنا عبد الله بن يوسف، قال أخبرنا مالك، عن عبد الله بن يزيد، وأبي النضر، مولى عمر بن عبيد الله عن أبي سلمة بن عبد الرحمن، عن عائشة أم المؤمنين ـ رضى الله عنها ـ أن رسول الله صلى الله عليه وسلم كان يصلي جالسا فيقرأ وهو جالس، فإذا بقي من قراءته نحو من ثلاثين أو أربعين آية قام فقرأها وهو قائم، ثم يركع ثم يسجد، يفعل في الركعة الثانية مثل ذلك، فإذا قضى صلاته نظر، فإن كنت يقظى تحدث معي، وإن كنت نائمة اضطجع‏.‏","grades":[],"reference":{"book":18,"hadith":39}}]}