{"metadata":{"name":"Sahih al Bukhari","section":{"96":"Holding Fast to the Qur'an and Sunnah"}},"hadiths":[{"hadithnumber":7369,"arabicnumber":7369,"text":"حدثنا الأويسي، حدثنا إبراهيم، عن صالح، عن ابن شهاب، حدثني عروة، وابن المسيب، وعلقمة بن وقاص، وعبيد الله، عن عائشة ـ رضى الله عنها ـ حين قال لها أهل الإفك قالت ودعا رسول الله صلى الله عليه وسلم علي بن أبي طالب وأسامة بن زيد حين استلبث الوحى يسألهما، وهو يستشيرهما في فراق أهله، فأما أسامة فأشار بالذي يعلم من براءة أهله، وأما علي فقال لم يضيق الله عليك، والنساء سواها كثير، وسل الجارية تصدقك‏.‏ فقال ‏\"‏ هل رأيت من شىء يريبك ‏\"‏‏.‏ قالت ما رأيت أمرا أكثر من أنها جارية حديثة السن تنام عن عجين أهلها فتأتي الداجن فتأكله‏.‏ فقام على المنبر فقال ‏\"‏ يا معشر المسلمين من يعذرني من رجل بلغني أذاه في أهلي، والله ما علمت على أهلي إلا خيرا ‏\"‏‏.‏ فذكر براءة عائشة‏.‏ وقال أبو أسامة عن هشام‏.‏","grades":[],"reference":{"book":96,"hadith":96}}]}