{
	"metadata": {
		"name": "Sunan Abu Dawud",
		"section": {
			"32": "Dialects and Readings of the Qur'an (Kitab Al-Huruf Wa Al-Qira'at)"
		}
	},
	"hadiths": [
		{
			"hadithnumber": 3999,
			"arabicnumber": 3999,
			"text": "Narrated AbuSa'id al-Khudri: The Messenger of Allah (ﷺ) mentioned the name of the one who will sound the trumpet (sahib as-sur) and said: On his right will be Jibra'il and on his left will be Mika'il",
			"grades": [
				{
					"name": "Al-Albani",
					"grade": "Daif"
				},
				{
					"name": "Muhammad Muhyi Al-Din Abdul Hamid",
					"grade": "Daif"
				},
				{
					"name": "Zubair Ali Zai",
					"grade": "Daif"
				}
			],
			"reference": {
				"book": 32,
				"hadith": 31
			}
		}
	]
}