{"metadata":{"name":"Sahih al Bukhari","section":{"59":"Beginning of Creation"}},"hadiths":[{"hadithnumber":3306,"arabicnumber":3306,"text":"ہم سے سعید بن عفیر نے بیان کیا، ان سے ابن وہب نے بیان کیا، کہا کہ مجھ سے یونس نے بیان کیا، ان سے ابن شہاب نے، ان سے عروہ نے، انہوں نے عائشہ رضی اللہ عنہا سے بیان کیا کہ نبی کریم صلی اللہ علیہ وسلم نے گرگٹ ( چھپکلی ) کے متعلق فرمایا کہ وہ موذی جانور ہے لیکن میں نے آپ صلی اللہ علیہ وسلم سے اسے مار ڈالنے کا حکم نہیں سنا تھا اور سعد بن ابی وقاص بتاتے تھے کہ نبی کریم صلی اللہ علیہ وسلم نے اسے مار ڈالنے کا حکم فرمایا ہے۔","grades":[],"reference":{"book":59,"hadith":114}}]}