{
	"metadata": {
		"name": "Sahih al Bukhari",
		"section": {
			"64": "Military Expeditions led by the Prophet (pbuh) (Al-Maghaazi)"
		}
	},
	"hadiths": [
		{
			"hadithnumber": 4170,
			"arabicnumber": 4170,
			"text": "مجھ سے احمد بن اشکاب نے بیان کیا ‘ کہا ہم سے محمد بن فضیل نے بیان کیا ‘ ان سے علاء بن مسیب نے ‘ ان سے ان کے والد نے بیان کیا کہ میں براء بن عازب رضی اللہ عنہ کی خدمت میں حاضر ہوا اور عرض کیا ‘ مبارک ہو! آپ کو نبی کریم صلی اللہ علیہ وسلم کی خدمت نصیب ہوئی اور نبی کریم صلی اللہ علیہ وسلم سے آپ نے شجر ( درخت ) کے نیچے بیعت کی۔ انہوں نے کہا بیٹے! تمہیں معلوم نہیں کہ ہم نے نبی کریم صلی اللہ علیہ وسلم کے بعد کیا کیا کام کئے ہیں۔",
			"grades": [],
			"reference": {
				"book": 64,
				"hadith": 212
			}
		}
	]
}