{
	"metadata": {
		"name": "Sunan Abu Dawud",
		"section": {
			"2": "Prayer (Kitab Al-Salat)"
		}
	},
	"hadiths": [
		{
			"hadithnumber": 1050,
			"arabicnumber": 1050,
			"text": "حدثنا مسدد، حدثنا أبو معاوية، عن الأعمش، عن أبي صالح، عن أبي هريرة، قال قال رسول الله صلى الله عليه وسلم ‏ \"‏ من توضأ فأحسن الوضوء ثم أتى الجمعة فاستمع وأنصت غفر له ما بين الجمعة إلى الجمعة وزيادة ثلاثة أيام ومن مس الحصى فقد لغا ‏\"‏ ‏.‏",
			"grades": [
				{
					"name": "Al-Albani",
					"grade": "Sahih"
				},
				{
					"name": "Muhammad Muhyi Al-Din Abdul Hamid",
					"grade": "Sahih"
				},
				{
					"name": "Shuaib Al Arnaut",
					"grade": "Sahih"
				},
				{
					"name": "Zubair Ali Zai",
					"grade": "Sahih Muslim"
				}
			],
			"reference": {
				"book": 2,
				"hadith": 661
			}
		}
	]
}