{"metadata":{"name":"Sunan Abu Dawud","section":{"29":"Medicine (Kitab Al-Tibb)"}},"hadiths":[{"hadithnumber":3887,"arabicnumber":3887,"text":"حدثنا إبراهيم بن مهدي المصيصي، حدثنا علي بن مسهر، عن عبد العزيز بن عمر بن عبد العزيز، عن صالح بن كيسان، عن أبي بكر بن سليمان بن أبي حثمة، عن الشفاء بنت عبد الله، قالت دخل على رسول الله صلى الله عليه وسلم وأنا عند حفصة فقال لي ‏ \"‏ ألا تعلمين هذه رقية النملة كما علمتيها الكتابة ‏\"‏ ‏.‏","grades":[{"name":"Al-Albani","grade":"Sahih"},{"name":"Muhammad Muhyi Al-Din Abdul Hamid","grade":"Sahih"},{"name":"Shuaib Al Arnaut","grade":"Sahih"},{"name":"Zubair Ali Zai","grade":"Sahih"}],"reference":{"book":29,"hadith":33}}]}