{
	"metadata": {
		"name": "Jami At Tirmidhi",
		"section": {
			"9": "The Book on Hajj"
		}
	},
	"hadiths": [
		{
			"hadithnumber": 883,
			"arabicnumber": 883,
			"text": "Yezîd b. Şeyban (radıyallahü anh)’den rivâyete göre, şöyle demiştir: İbn Mirba’ el Ensarî biz Arafat’ta iken yanımıza geldi, Biz Amr’ın vakfe yerinden uzak saydığı bir yerde idik ve şöyle dedi. “Ben Rasûlüllah (sallallahü aleyhi ve sellem)’in size gönderdiği elçisiyim o size “İbadet yerleriniz neresi ise orada bulunun çünkü siz atanız İbrahim (aleyhis-selâm)’dan kalma bir miras üzerindesiniz.” (Ebû Dâvûd, Menasik: 62; Buhârî, Hac: 87) Bu konuda Ali, Âişe, Cübeyr b. Mut’ım ve Şerid b. Süveyd es Sekafî’den de hadis rivâyet edilmiştir. İbn Mirba’ el Ensarî hadisi hasen sahihtir. Bu hadisi sadece İbn Uyeyne’nin Amr b. Dinar’dan, yaptığı rivâyetle bilmekteyiz. İbn Mirba’nın ismi Yezîd b. Mirba’ el Ensarî’dir. Onun rivâyeti olarak tek bir hadis bilinmektedir",
			"grades": [
				{
					"name": "Ahmad Muhammad Shakir",
					"grade": "Sahih"
				},
				{
					"name": "Al-Albani",
					"grade": "Sahih"
				},
				{
					"name": "Zubair Ali Zai",
					"grade": "Isnaad Sahih"
				}
			],
			"reference": {
				"book": 9,
				"hadith": 76
			}
		}
	]
}